{
  "m_Version": 12,
  "DisplayName": "VEHICLE PARTS",
  "MinRequiredReputation": 0,
  "MaxRequiredReputation": 2147483647,
  "RequiredFaction": "0",
  "RequiredCompletedQuestID": -1,
  "TraderIcon": "Wheel",
  "Currencies": [
    "ExpansionBanknoteEuro",
    "BTC_Currency_Coin_1",
    "BTC_Currency_Note_5",
    "BTC_Currency_Note_10",
    "BTC_Currency_Note_20",
    "BTC_Currency_Note_50",
    "BTC_Currency_Note_100",
    "BTC_Currency_Note_200",
    "BTC_Currency_Note_500",
    "BTC_Currency_Case_1000",
    "BTC_Currency_Case_10000",
    "BTC_Currency_Barrel_1000000"
  ],
  "DisplayCurrencyValue": 1,
  "DisplayCurrencyName": "",
  "Categories": [
    "AutoZone",
    "Parts_4Runner",
    "Parts_Audi",
    "Parts_BMW",
    "Parts_BRONCO",
    "Parts_CHALLENGER",
    "Parts_CIVIC",
    "Parts_DoorsVanilla",
    "Parts_GMC",
    "Parts_HellCat",
    "Parts_JEEP",
    "Parts_LANCEREVO",
    "Parts_MOTORHOME",
    "Parts_MONSTERTRUCK",
    "Parts_NOVA",
    "Parts_NissanGTR",
    "Parts_NissanGTRNISMO",
    "Parts_NissanGTRCUSTOM",
    "Parts_Porsche",
    "Parts_Supra",
    "Parts_SKYLINE",
    "Parts_TAHOE",
    "Parts_TYPHOONK",
    "Parts_RAMs",
    "Parts_RAM3500",
    "Parts_3500FrontBumper"
  ],
  "Items": {}
}